wolfsoftware/get_aws_regions/__init__.py
wolfsoftware/get_aws_regions/exceptions.py
wolfsoftware/get_aws_regions/functions.py
wolfsoftware.get_aws_regions-0.1.2.dist-info/LICENSE.md
wolfsoftware.get_aws_regions-0.1.2.dist-info/METADATA
wolfsoftware.get_aws_regions-0.1.2.dist-info/WHEEL
wolfsoftware.get_aws_regions-0.1.2.dist-info/top_level.txt
wolfsoftware.get_aws_regions-0.1.2.dist-info/RECORD
