Metadata-Version: 2.1
Name: wolfsoftware.get-aws-regions
Version: 0.1.2
Summary: A simple package for retrieving a list of AWS regions.
Home-page: https://github.com/AWSToolbox/get-aws-regions-package
Author: Wolf Software
Author-email: pypi@wolfsoftware.com
License: MIT
Project-URL: Source, https://github.com/AWSToolbox/get-aws-regions-package
Project-URL: Tracker, https://github.com/AWSToolbox/get-aws-regions-package/issues/
Project-URL: Documentation, https://github.com/AWSToolbox/get-aws-regions-package
Project-URL: Sponsor, https://github.com/sponsors/WolfSoftware
Keywords: python,aws,regions
Classifier: Development Status :: 4 - Beta
Classifier: Environment :: Console
Classifier: Intended Audience :: Developers
Classifier: License :: OSI Approved :: MIT License
Classifier: Programming Language :: Python :: 3
Classifier: Programming Language :: Python :: 3.9
Classifier: Programming Language :: Python :: 3.10
Classifier: Programming Language :: Python :: 3.11
Classifier: Programming Language :: Python :: 3.12
Classifier: Operating System :: OS Independent
Classifier: Topic :: Software Development
Requires-Python: >=3.9
License-File: LICENSE.md
Requires-Dist: botocore ==1.34.134
Requires-Dist: boto3 ==1.34.134
